trytond/modules/irrulecontext/README.rst
trytond/modules/irrulecontext/__init__.py
trytond/modules/irrulecontext/ir.py
trytond/modules/irrulecontext/tryton.cfg
trytond/modules/irrulecontext/versiondep.txt
trytond/modules/irrulecontext/tests/__init__.py
trytond/modules/irrulecontext/tests/addonvalues.py
trytond/modules/irrulecontext/tests/irrule.py
trytond/modules/irrulecontext/tests/test_module.py
mds_irrulecontext-7.0.1.dist-info/LICENSE
mds_irrulecontext-7.0.1.dist-info/METADATA
mds_irrulecontext-7.0.1.dist-info/WHEEL
mds_irrulecontext-7.0.1.dist-info/entry_points.txt
mds_irrulecontext-7.0.1.dist-info/top_level.txt
mds_irrulecontext-7.0.1.dist-info/RECORD
